odoo10_addon_account_type_multi_company-10.0.1.0.0-py2.7-nspkg.pth
odoo/addons/account_type_multi_company/README.rst
odoo/addons/account_type_multi_company/__init__.py
odoo/addons/account_type_multi_company/__manifest__.py
odoo/addons/account_type_multi_company/models/__init__.py
odoo/addons/account_type_multi_company/models/account_account_type.py
odoo/addons/account_type_multi_company/security/account_account_type.xml
odoo/addons/account_type_multi_company/static/description/icon.png
odoo/addons/account_type_multi_company/views/account_account_type.xml
odoo10_addon_account_type_multi_company-10.0.1.0.0.dist-info/DESCRIPTION.rst
odoo10_addon_account_type_multi_company-10.0.1.0.0.dist-info/METADATA
odoo10_addon_account_type_multi_company-10.0.1.0.0.dist-info/RECORD
odoo10_addon_account_type_multi_company-10.0.1.0.0.dist-info/WHEEL
odoo10_addon_account_type_multi_company-10.0.1.0.0.dist-info/metadata.json
odoo10_addon_account_type_multi_company-10.0.1.0.0.dist-info/namespace_packages.txt
odoo10_addon_account_type_multi_company-10.0.1.0.0.dist-info/top_level.txt
